nr_ops/__init__.py
nr_ops/config/__init__.py
nr_ops/config/main_config.py
nr_ops/main.py
nr_ops/main_lambda.py
nr_ops/messages/__init__.py
nr_ops/messages/op_audit.py
nr_ops/messages/op_metadata.py
nr_ops/messages/op_msg.py
nr_ops/messages/time_step.py
nr_ops/ops/__init__.py
nr_ops/ops/base.py
nr_ops/ops/op.py
nr_ops/ops/op_collection.py
nr_ops/ops/op_manager.py
nr_ops/ops/ops/__init__.py
nr_ops/ops/ops/connector_ops/__init__.py
nr_ops/ops/ops/connector_ops/hooks/__init__.py
nr_ops/ops/ops/connector_ops/hooks/airflow_gcp_bigquery_hook.py
nr_ops/ops/ops/connector_ops/hooks/airflow_gcp_gcs_hook.py
nr_ops/ops/ops/connector_ops/hooks/airflow_gcp_hook.py
nr_ops/ops/ops/connector_ops/hooks/airflow_mysql_hook.py
nr_ops/ops/ops/connector_ops/hooks/airflow_postgres_hook.py
nr_ops/ops/ops/connector_ops/hooks/airflow_s3_hook.py
nr_ops/ops/ops/connector_ops/hooks/gcp_service_account_from_file.py
nr_ops/ops/ops/connector_ops/hooks/http_requests_from_env.py
nr_ops/ops/ops/connector_ops/hooks/python_counter.py
nr_ops/ops/ops/connector_ops/hooks/python_file.py
nr_ops/ops/ops/connector_ops/hooks/python_list.py
nr_ops/ops/ops/connector_ops/hooks/python_queue.py
nr_ops/ops/ops/connector_ops/interfaces/__init__.py
nr_ops/ops/ops/connector_ops/interfaces/base.py
nr_ops/ops/ops/connector_ops/interfaces/counter.py
nr_ops/ops/ops/connector_ops/interfaces/file.py
nr_ops/ops/ops/connector_ops/interfaces/gcp_bigquery.py
nr_ops/ops/ops/connector_ops/interfaces/gcp_gcs.py
nr_ops/ops/ops/connector_ops/interfaces/google_ads.py
nr_ops/ops/ops/connector_ops/interfaces/google_analytics.py
nr_ops/ops/ops/connector_ops/interfaces/google_analytics_ga4.py
nr_ops/ops/ops/connector_ops/interfaces/google_sheets.py
nr_ops/ops/ops/connector_ops/interfaces/http.py
nr_ops/ops/ops/connector_ops/interfaces/list.py
nr_ops/ops/ops/connector_ops/interfaces/mysql.py
nr_ops/ops/ops/connector_ops/interfaces/postgres.py
nr_ops/ops/ops/connector_ops/interfaces/queue.py
nr_ops/ops/ops/connector_ops/interfaces/s3.py
nr_ops-0.27.1.0.dist-info/LICENSE
nr_ops-0.27.1.0.dist-info/METADATA
nr_ops-0.27.1.0.dist-info/WHEEL
nr_ops-0.27.1.0.dist-info/entry_points.txt
nr_ops-0.27.1.0.dist-info/RECORD
