Metadata-Version: 2.1
Name: nr-ops
Version: 0.27.1.0
Summary: An opinionated operator framework.
Author: Nitish Reddy Koripalli
Author-email: nitish.k.reddy@gmail.com
Requires-Python: >=3.9,<3.10
Classifier: Programming Language :: Python :: 3
Classifier: Programming Language :: Python :: 3.9
Requires-Dist: Jinja2 (==3.1.2)
Requires-Dist: apache-airflow[amazon,cncf-kubernetes,common-sql,ftp,google,http,imap,mysql,postgres,sftp,sqlite,ssh] (==2.5.1)
Requires-Dist: backoff (==2.2.1)
Requires-Dist: dbt-core (==1.4.5)
Requires-Dist: dbt-postgres (==1.4.5)
Requires-Dist: google-ads (==23.0.0)
Requires-Dist: google-analytics-data (==0.16.1)
Requires-Dist: google-cloud-bigquery (==3.7.0)
Requires-Dist: google-cloud-storage (==1.44.0)
Requires-Dist: joblib (==1.2.0)
Requires-Dist: matplotlib (==3.7.1)
Requires-Dist: oauth2client (==4.1.3)
Requires-Dist: openpyxl (==3.1.1)
Requires-Dist: pandas (==1.5.3)
Requires-Dist: pangres (==4.1.2)
Requires-Dist: pydantic (==1.10.13)
Requires-Dist: requests-futures (==1.0.1)
Requires-Dist: ruamel.yaml (==0.17.21)
Requires-Dist: scikit-learn (==1.2.2)
Requires-Dist: scipy (==1.10.1)
Requires-Dist: threadpoolctl (==3.1.0)
Requires-Dist: zeep (==4.2.1)
Requires-Dist: zstandard (==0.19.0)
